{
	"format_version": "1.8.0",
	"animations": {
		"raider.idle": {
			"loop": true,
			"animation_length": 4,
			"bones": {
				"nose": {
					"rotation": {
						"0.0": [0, 0, 5],
						"2.0": [0, 0, -5],
						"4.0": [0, 0, 5]
					}
				},
				"Body": {
					"rotation": {
						"0.0": [0, 0, 0],
						"2.0": [2.5, 0, 0],
						"4.0": [0, 0, 0]
					}
				},
				"arms": {
					"rotation": [-17.5, 0, 0]
				},
				"RightArm": {
					"rotation": {
						"0.0": [-47.8518, -16.97131, -14.9625],
						"2.0": [-42.8518, -16.97131, -14.9625],
						"4.0": [-47.8518, -16.97131, -14.9625]
					},
					"position": {
						"0.0": [0, -0.75, -1],
						"4.0": [0, -0.75, -1]
					}
				},
				"LeftArm": {
					"rotation": {
						"0.0": [-45.28089, 35.39626, 29.83757],
						"2.0": [-40.28089, 35.39626, 29.83757],
						"4.0": [-45.28089, 35.39626, 29.83757]
					},
					"position": {
						"0.0": [-0.25, -2, -1.75],
						"4.0": [-0.25, -2, -1.75]
					}
				},
				"hands": {
					"scale": 0
				},
				"left": {
					"rotation": {
						"0.0": [-28.48124, 9.84655, 17.49524],
						"2.0": [-23.06213, 10.83442, 19.82974],
						"4.0": [-28.48124, 9.84655, 17.49524]
					},
					"position": {
						"0.0": [0, -1.75, 0.25],
						"2.0": [0, -1.75, 0],
						"4.0": [0, -1.75, 0.25]
					}
				},
				"right": {
					"rotation": {
						"0.0": [-31.70533, -6.87607, -15.97035],
						"2.0": [-26.70533, -6.87607, -15.97035],
						"4.0": [-31.70533, -6.87607, -15.97035]
					},
					"position": {
						"0.0": [0, -1, 1.25],
						"2.0": [0, -1, 0.75],
						"4.0": [0, -1, 1.25]
					}
				}
			}
		},
		"raider.move": {
			"loop": true,
			"animation_length": 2,
			"bones": {
				"nose": {
					"rotation": {
						"0.0": {
							"vector": [0, 0, 2.5]
						},
						"0.5": {
							"vector": [0, 0, -2.5]
						},
						"1.0": {
							"vector": [0, 0, 2.5]
						},
						"1.5": {
							"vector": [0, 0, -2.5]
						},
						"2.0": {
							"vector": [0, 0, 2.5]
						}
					}
				},
				"Body": {
					"rotation": {
						"0.0": {
							"vector": [-5, 0, 0]
						},
						"0.5": {
							"vector": [0, 0, 0]
						},
						"1.0": {
							"vector": [-5, 0, 0]
						},
						"1.5": {
							"vector": [0, 0, 0]
						},
						"2.0": {
							"vector": [-5, 0, 0]
						}
					}
				},
				"arms": {
					"rotation": {
						"vector": [-17.5, 0, 0]
					}
				},
				"RightArm": {
					"rotation": {
						"0.0": {
							"vector": [-47.8518, -16.97131, -14.9625]
						},
						"0.5417": {
							"vector": [-42.8518, -16.97131, -14.9625],
							"easing": "linear"
						},
						"1.0": {
							"vector": [-47.8518, -16.97131, -14.9625],
							"easing": "linear"
						},
						"1.5417": {
							"vector": [-42.8518, -16.97131, -14.9625],
							"easing": "linear"
						},
						"2.0": {
							"vector": [-47.8518, -16.97131, -14.9625],
							"easing": "linear"
						}
					},
					"position": {
						"0.0": {
							"vector": [0, -0.75, -1]
						},
						"1.0": {
							"vector": [0, -0.75, -1]
						},
						"2.0": {
							"vector": [0, -0.75, -1]
						}
					}
				},
				"LeftArm": {
					"rotation": {
						"0.0": {
							"vector": [-45.28089, 35.39626, 29.83757]
						},
						"0.5417": {
							"vector": [-40.28089, 35.39626, 29.83757],
							"easing": "linear"
						},
						"1.0": {
							"vector": [-45.28089, 35.39626, 29.83757],
							"easing": "linear"
						},
						"1.5417": {
							"vector": [-40.28089, 35.39626, 29.83757],
							"easing": "linear"
						},
						"2.0": {
							"vector": [-45.28089, 35.39626, 29.83757],
							"easing": "linear"
						}
					},
					"position": {
						"0.0": {
							"vector": [-0.25, -2, -1.75]
						},
						"1.0": {
							"vector": [-0.25, -2, -1.75]
						},
						"2.0": {
							"vector": [-0.25, -2, -1.75]
						}
					}
				},
				"hands": {
					"scale": {
						"vector": [0, 0, 0]
					}
				},
				"main": {
					"rotation": {
						"0.0": {
							"vector": [0, 0, -1.2]
						},
						"1.0": {
							"vector": [0, 0, 1.2]
						},
						"2.0": {
							"vector": [0, 0, -1.2]
						}
					},
					"position": {
						"0.0": {
							"vector": [0, -1, 0]
						},
						"0.5": {
							"vector": [0, 0, 0]
						},
						"1.0": {
							"vector": [0, -1, 0]
						},
						"1.5": {
							"vector": [0, 0, 0]
						},
						"2.0": {
							"vector": [0, -1, 0]
						}
					}
				},
				"left": {
					"rotation": {
						"0.0": {
							"vector": [-27.62113, 12.19908, 21.99054]
						},
						"0.5417": {
							"vector": [-23.06213, 10.83442, 19.82974]
						},
						"1.0": {
							"vector": [-27.62113, 12.19908, 21.99054]
						},
						"1.5417": {
							"vector": [-23.06213, 10.83442, 19.82974]
						},
						"2.0": {
							"vector": [-27.62113, 12.19908, 21.99054]
						}
					},
					"position": {
						"0.0": {
							"vector": [0, -1.75, 0.25]
						},
						"0.5417": {
							"vector": [0, -1.75, 0]
						},
						"1.0": {
							"vector": [0, -1.75, 0.25]
						},
						"1.5417": {
							"vector": [0, -1.75, 0]
						},
						"2.0": {
							"vector": [0, -1.75, 0.25]
						}
					}
				},
				"right": {
					"rotation": {
						"0.0": {
							"vector": [-34.20533, -6.87607, -15.97035]
						},
						"0.5417": {
							"vector": [-26.70533, -6.87607, -15.97035]
						},
						"1.0": {
							"vector": [-34.20533, -6.87607, -15.97035]
						},
						"1.5417": {
							"vector": [-26.70533, -6.87607, -15.97035]
						},
						"2.0": {
							"vector": [-34.20533, -6.87607, -15.97035]
						}
					},
					"position": {
						"0.0": {
							"vector": [0, -1, 1.25]
						},
						"0.5417": {
							"vector": [0, -1, 0.75]
						},
						"1.0": {
							"vector": [0, -1, 1.25]
						},
						"1.5417": {
							"vector": [0, -1, 0.75]
						},
						"2.0": {
							"vector": [0, -1, 1.25]
						}
					}
				}
			}
		},
		"raider.move2": {
			"loop": true,
			"animation_length": 2,
			"bones": {
				"nose": {
					"rotation": {
						"0.0": {
							"vector": [0, 0, 2.5]
						},
						"0.5": {
							"vector": [0, 0, -2.5]
						},
						"1.0": {
							"vector": [0, 0, 2.5]
						},
						"1.5": {
							"vector": [0, 0, -2.5]
						},
						"2.0": {
							"vector": [0, 0, 2.5]
						}
					}
				},
				"Body": {
					"rotation": {
						"0.0": {
							"vector": [-5, 0, 0]
						},
						"0.5": {
							"vector": [0, 0, 0]
						},
						"1.0": {
							"vector": [-5, 0, 0]
						},
						"1.5": {
							"vector": [0, 0, 0]
						},
						"2.0": {
							"vector": [-5, 0, 0]
						}
					}
				},
				"arms": {
					"rotation": {
						"vector": [-17.5, 0, 0]
					}
				},
				"RightArm": {
					"rotation": {
						"0.0": {
							"vector": [-77.78446, -21.96769, -15.16434]
						},
						"0.5417": {
							"vector": [-60.3518, -16.97131, -14.9625]
						},
						"1.0": {
							"vector": [-77.78446, -21.96769, -15.16434]
						},
						"1.5417": {
							"vector": [-60.3518, -16.97131, -14.9625]
						},
						"2.0": {
							"vector": [-77.78446, -21.96769, -15.16434]
						}
					},
					"position": {
						"0.0": {
							"vector": [0, -0.75, -1]
						},
						"0.5417": {
							"vector": [0, -0.5, -1]
						},
						"1.0": {
							"vector": [0, -0.75, -1]
						},
						"1.5417": {
							"vector": [0, -0.5, -1]
						},
						"2.0": {
							"vector": [0, -0.75, -1]
						}
					}
				},
				"LeftArm": {
					"rotation": {
						"0.0": {
							"vector": [-66.27165, 40.00052, 32.30341]
						},
						"0.5417": {
							"vector": [-52.78089, 35.39626, 29.83757]
						},
						"1.0": {
							"vector": [-66.27165, 40.00052, 32.30341]
						},
						"1.5417": {
							"vector": [-52.78089, 35.39626, 29.83757]
						},
						"2.0": {
							"vector": [-66.27165, 40.00052, 32.30341]
						}
					},
					"position": {
						"0.0": {
							"vector": [-0.25, -2, -1.75]
						},
						"0.5417": {
							"vector": [-0.25, -1.5, -1.75]
						},
						"1.0": {
							"vector": [-0.25, -2, -1.75]
						},
						"1.5417": {
							"vector": [-0.25, -1.5, -1.75]
						},
						"2.0": {
							"vector": [-0.25, -2, -1.75]
						}
					}
				},
				"hands": {
					"scale": {
						"vector": [0, 0, 0]
					}
				},
				"main": {
					"rotation": {
						"0.0": {
							"vector": [0, 0, -1.2]
						},
						"1.0": {
							"vector": [0, 0, 1.2]
						},
						"2.0": {
							"vector": [0, 0, -1.2]
						}
					},
					"position": {
						"0.0": {
							"vector": [0, -1, 0]
						},
						"0.5": {
							"vector": [0, 0, 0]
						},
						"1.0": {
							"vector": [0, -1, 0]
						},
						"1.5": {
							"vector": [0, 0, 0]
						},
						"2.0": {
							"vector": [0, -1, 0]
						}
					}
				},
				"left": {
					"rotation": {
						"0.0": {
							"vector": [-59.11466, 30.12179, 31.56635]
						},
						"0.5417": {
							"vector": [-31.02299, 16.15044, 28.5442]
						},
						"1.0": {
							"vector": [-59.11466, 30.12179, 31.56635]
						},
						"1.5417": {
							"vector": [-31.02299, 16.15044, 28.5442]
						},
						"2.0": {
							"vector": [-59.11466, 30.12179, 31.56635]
						}
					},
					"position": {
						"0.0": {
							"vector": [0.25, -4.5, 1]
						},
						"0.5417": {
							"vector": [0, -2, 0]
						},
						"1.0": {
							"vector": [0.25, -4.5, 1]
						},
						"1.5417": {
							"vector": [0, -2, 0]
						},
						"2.0": {
							"vector": [0.25, -4.5, 1]
						}
					}
				},
				"right": {
					"rotation": {
						"0.0": {
							"vector": [-56.70533, -6.87607, -15.97035]
						},
						"0.5417": {
							"vector": [-39.20533, -6.87607, -15.97035]
						},
						"1.0": {
							"vector": [-54.20533, -6.87607, -15.97035]
						},
						"1.5417": {
							"vector": [-39.20533, -6.87607, -15.97035]
						},
						"2.0": {
							"vector": [-54.20533, -6.87607, -15.97035]
						}
					},
					"position": {
						"0.0": {
							"vector": [0, -2, 1.25]
						},
						"0.5417": {
							"vector": [0, -1, 0.75]
						},
						"1.0": {
							"vector": [0, -1.75, 1.25]
						},
						"1.5417": {
							"vector": [0, -1, 0.75]
						},
						"2.0": {
							"vector": [0, -1.75, 1.25]
						}
					}
				},
				"Head": {
					"rotation": {
						"0.0": {
							"vector": [-2.5, 0, 5]
						},
						"0.5417": {
							"vector": [2.49762, 0.10901, 2.50238]
						},
						"1.0": {
							"vector": [-2.5, 0, 5]
						},
						"1.5417": {
							"vector": [2.49762, -0.10901, 7.49762]
						},
						"2.0": {
							"vector": [-2.5, 0, 5]
						}
					}
				}
			}
		},
		"raider.attack": {
			"animation_length": 3.2,
			"bones": {
				"Head": {
					"rotation": {
						"0.0": {
							"vector": [-16.79133, 3.65727, 14.43758]
						},
						"2.0": {
							"vector": [20.66899, 6.20987, 3.62348]
						},
						"3.0": {
							"vector": [0, 0, 0]
						}
					},
					"position": {
						"0.0": {
							"vector": [0, 1, 1]
						},
						"2.0": {
							"vector": [0, 0.25, -5]
						},
						"3.0": {
							"vector": [0, 0, 0]
						}
					}
				},
				"Body": {
					"rotation": {
						"0.0": {
							"vector": [-5, 0, 0]
						},
						"2.0": {
							"vector": [17.5, 0, 0]
						},
						"3.0": {
							"vector": [0, 0, 0]
						}
					},
					"position": {
						"0.0": {
							"vector": [0, 0, 1]
						},
						"2.0": {
							"vector": [0, 0, -4]
						},
						"3.0": {
							"vector": [0, 0, 0]
						}
					}
				},
				"RightArm": {
					"rotation": {
						"0.0": {
							"vector": [-141.55833, -10.35868, 23.59924]
						},
						"2.0": {
							"vector": [-25.21399, -3.93893, 14.02181]
						},
						"3.0": {
							"vector": [-47.8518, -16.97131, -14.9625]
						}
					},
					"position": {
						"0.0": {
							"vector": [-1.25, 1, -2]
						},
						"2.0": {
							"vector": [-1.25, -2.5, -4.5]
						},
						"3.0": {
							"vector": [0, -0.75, -1]
						}
					}
				},
				"LeftArm": {
					"rotation": {
						"0.0": {
							"vector": [-146.14897, 52.77737, -29.81581]
						},
						"2.0": {
							"vector": [-32.5, 0, -20]
						},
						"3.0": {
							"vector": [-45.28089, 35.39626, 29.83757]
						}
					},
					"position": {
						"0.0": {
							"vector": [-1.25, 1, -4]
						},
						"2.0": {
							"vector": [1.25, -2, -3.5]
						},
						"3.0": {
							"vector": [-0.25, -2, -1.75]
						}
					}
				},
				"hands": {
					"scale": {
						"0.0": {
							"vector": [0, 0, 0]
						},
						"3.0": {
							"vector": [0, 0, 0]
						}
					}
				},
				"main": {
					"rotation": {
						"0.0": {
							"vector": [0, 0, 2.5]
						},
						"2.0": {
							"vector": [0, 0, 0]
						},
						"3.0": {
							"vector": [0, 0, 0]
						}
					}
				},
				"left": {
					"rotation": {
						"0.0": {
							"vector": [-111.69435, 51.98839, 6.42704]
						},
						"2.0": {
							"vector": [-27.5, 0, -12.5]
						},
						"3.0": {
							"vector": [-28.48124, 9.84655, 17.49524]
						}
					},
					"position": {
						"0.0": {
							"vector": [-0.25, -4.75, -3.25]
						},
						"2.0": {
							"vector": [0, 0, -2]
						},
						"3.0": {
							"vector": [0, -1.75, 0.25]
						}
					}
				},
				"right": {
					"rotation": {
						"0.0": {
							"vector": [-130.83291, -2.88285, 16.90041]
						},
						"2.0": {
							"vector": [-24.56544, -2.33214, 16.80367]
						},
						"3.0": {
							"vector": [-31.70533, -6.87607, -15.97035]
						}
					},
					"position": {
						"0.0": {
							"vector": [0, -3, 0.25]
						},
						"1.0": {
							"vector": [0.25, -1.75, 1.5]
						},
						"2.0": {
							"vector": [0.5, -1, -3.25]
						},
						"3.0": {
							"vector": [0, -1, 1.25]
						}
					}
				},
				"nose": {
					"rotation": {
						"vector": [0, 0, 5]
					}
				},
				"arms": {
					"rotation": {
						"vector": [-17.5, 0, 0]
					}
				}
			}
		},
		"raider.sit": {
			"loop": true,
			"animation_length": 4,
			"bones": {
				"nose": {
					"rotation": {
						"0.0": {
							"vector": [0, 0, 5]
						},
						"2.0": {
							"vector": [0, 0, -5]
						},
						"4.0": {
							"vector": [0, 0, 5]
						}
					}
				},
				"Body": {
					"rotation": {
						"0.0": {
							"vector": [-2.5, 0, 0]
						},
						"2.0": {
							"vector": [2, 0, 0]
						},
						"4.0": {
							"vector": [-2.5, 0, 0]
						}
					}
				},
				"arms": {
					"rotation": {
						"0.0": {
							"vector": [-50, 0, 0]
						},
						"4.0": {
							"vector": [-50, 0, 0]
						}
					},
					"position": {
						"0.0": {
							"vector": [0, 0, 0]
						},
						"2.0": {
							"vector": [0, -1, 0]
						},
						"4.0": {
							"vector": [0, 0, 0]
						}
					}
				},
				"RightLeg": {
					"rotation": {
						"vector": [-47.38443, 0.75155, 17.48436]
					}
				},
				"LeftLeg": {
					"rotation": {
						"vector": [-49.91492, -0.64686, -14.98637]
					}
				},
				"RightArm": {
					"rotation": {
						"0.0": {
							"vector": [-50, 0, 0]
						},
						"4.0": {
							"vector": [-50, 0, 0]
						}
					},
					"position": {
						"0.0": {
							"vector": [0, 0, 0]
						},
						"2.0": {
							"vector": [0, -1, 0]
						},
						"4.0": {
							"vector": [0, 0, 0]
						}
					},
					"scale": {
						"vector": [0.9, 0.5, 1]
					}
				},
				"LeftArm": {
					"rotation": {
						"0.0": {
							"vector": [-50, 0, 0]
						},
						"4.0": {
							"vector": [-50, 0, 0]
						}
					},
					"position": {
						"0.0": {
							"vector": [0, 0, 0]
						},
						"2.0": {
							"vector": [0, -1, 0]
						},
						"4.0": {
							"vector": [0, 0, 0]
						}
					},
					"scale": {
						"vector": [0.975, 0.5, 1]
					}
				},
				"pauldrons": {
					"position": {
						"vector": [0, -1, 0]
					}
				},
				"hands": {
					"position": {
						"vector": [0, -4, 0]
					}
				},
				"main": {
					"rotation": {
						"0.0": {
							"vector": [0, 0, 0]
						},
						"2.0": {
							"vector": [0, 0, 0]
						},
						"4.0": {
							"vector": [2.5, 0, 0]
						}
					},
					"position": {
						"vector": [0, -7, 0]
					}
				}
			}
		},
		"raider.legs1": {
			"loop": true,
			"bones": {
				"LeftLeg": {
					"rotation": {
						"vector": ["-math.sin(query.anim_time*180)*20", 0, 0]
					},
					"position": {
						"vector": [0, "math.clamp(math.cos(query.anim_time*180)*2,0,3)", 0]
					}
				},
				"RightLeg": {
					"rotation": {
						"vector": ["math.sin(query.anim_time*180)*20", 0, 0]
					},
					"position": {
						"vector": [0, "math.clamp(-math.cos(query.anim_time*180)*2,0,3)", 0]
					}
				}
			}
		},
		"raider.legs2": {
			"loop": true
		}
	},
	"geckolib_format_version": 2
}